polymaze/cli.py
polymaze/maze.py
polymaze/polygrid.py
polymaze/shapes.py
polymaze/__init__.py
polymaze/__main__.py
polymaze/font/LICENSE_CJK.txt
polymaze/font/NotoSansCJK-Bold.ttc
polymaze-0.7.0.dist-info/DESCRIPTION.rst
polymaze-0.7.0.dist-info/entry_points.txt
polymaze-0.7.0.dist-info/METADATA
polymaze-0.7.0.dist-info/metadata.json
polymaze-0.7.0.dist-info/RECORD
polymaze-0.7.0.dist-info/top_level.txt
polymaze-0.7.0.dist-info/WHEEL
