Metadata-Version: 2.0
Name: polymaze
Version: 0.7.0
Summary: Create polygon-tesselation mazes from a variety of sources.
Home-page: https://github.com/kobejohn/polymaze
Author: John Nieri
Author-email: niericentral@gmail.com
License: MIT
Keywords: mazes tesselation
Platform: UNKNOWN
Classifier: Development Status :: 3 - Alpha
Classifier: Intended Audience :: Developers
Classifier: Topic :: Artistic Software
Classifier: License :: OSI Approved :: MIT License
Classifier: Programming Language :: Python :: 2
Classifier: Programming Language :: Python :: 3
Requires-Dist: PILLOW
